optimum/deepsparse/__init__.py
optimum/deepsparse/modeling.py
optimum/deepsparse/modeling_base.py
optimum/deepsparse/modeling_diffusion.py
optimum/deepsparse/version.py
optimum_deepsparse-0.1.0.dev1.dist-info/LICENSE
optimum_deepsparse-0.1.0.dev1.dist-info/LICENSE-NEURALMAGIC
optimum_deepsparse-0.1.0.dev1.dist-info/METADATA
optimum_deepsparse-0.1.0.dev1.dist-info/WHEEL
optimum_deepsparse-0.1.0.dev1.dist-info/entry_points.txt
optimum_deepsparse-0.1.0.dev1.dist-info/top_level.txt
optimum_deepsparse-0.1.0.dev1.dist-info/RECORD
