Metadata-Version: 2.1
Name: optimum-deepsparse
Version: 0.1.0.dev1
Summary: Optimum DeepSparse is an extension of the Hugging Face Transformers library that integrates the DeepSparse inference runtime. DeepSparse offers GPU-class performance on CPUs, making it possible to run Transformers and other deep learning models on commodity hardware with sparsity. Optimum DeepSparse provides a framework for developers to easily integrate DeepSparse into their applications, regardless of the hardware platform.
Home-page: https://github.com/neuralmagic/deepsparse
Author: Neuralmagic, Inc.
Author-email: michael@neuralmagic.com
License: Neural Magic DeepSparse Community License, Apache
Keywords: inference,cpu,x86,arm,transformers,quantization,pruning,sparsity
Platform: UNKNOWN
Classifier: Development Status :: 5 - Production/Stable
Classifier: License :: OSI Approved :: Apache Software License
Classifier: Intended Audience :: Developers
Classifier: Intended Audience :: Education
Classifier: Intended Audience :: Science/Research
Classifier: Operating System :: OS Independent
Classifier: Programming Language :: Python :: 3.8
Classifier: Programming Language :: Python :: 3.9
Classifier: Programming Language :: Python :: 3.10
Classifier: Topic :: Scientific/Engineering :: Artificial Intelligence
Requires-Python: >=3.8, <3.11
License-File: LICENSE
License-File: LICENSE-NEURALMAGIC
Requires-Dist: deepsparse-nightly
Requires-Dist: optimum[exporters] ==1.13.2
Requires-Dist: diffusers ==0.21.4
Provides-Extra: dev
Requires-Dist: pytest ; extra == 'dev'
Requires-Dist: parameterized ; extra == 'dev'
Requires-Dist: Pillow ; extra == 'dev'
Requires-Dist: evaluate ; extra == 'dev'
Requires-Dist: diffusers ; extra == 'dev'
Requires-Dist: py-cpuinfo ; extra == 'dev'
Requires-Dist: torchaudio ; extra == 'dev'
Requires-Dist: black ~=23.1 ; extra == 'dev'
Requires-Dist: ruff <=0.0.259,>=0.0.241 ; extra == 'dev'
Provides-Extra: quality
Requires-Dist: black ~=23.1 ; extra == 'quality'
Requires-Dist: ruff <=0.0.259,>=0.0.241 ; extra == 'quality'
Provides-Extra: tests
Requires-Dist: pytest ; extra == 'tests'
Requires-Dist: parameterized ; extra == 'tests'
Requires-Dist: Pillow ; extra == 'tests'
Requires-Dist: evaluate ; extra == 'tests'
Requires-Dist: diffusers ; extra == 'tests'
Requires-Dist: py-cpuinfo ; extra == 'tests'
Requires-Dist: torchaudio ; extra == 'tests'
